streamlit_chat_animated/__init__.py
streamlit_chat_animated/frontend/build/asset-manifest.json
streamlit_chat_animated/frontend/build/bootstrap.min.css
streamlit_chat_animated/frontend/build/bootstrap.min.css.map
streamlit_chat_animated/frontend/build/index.html
streamlit_chat_animated/frontend/build/precache-manifest.0c02e5679f95ab531f5daa41cbcc3366.js
streamlit_chat_animated/frontend/build/precache-manifest.0e7f2b7014ea657137044c8cbc791e0e.js
streamlit_chat_animated/frontend/build/precache-manifest.230db9bd95594a43c51ef55435bd1bb4.js
streamlit_chat_animated/frontend/build/precache-manifest.3b0a591d4a4841e4c5b66ac197cf38fa.js
streamlit_chat_animated/frontend/build/precache-manifest.42adc6ee089b9b6a2b593390555498ec.js
streamlit_chat_animated/frontend/build/precache-manifest.5e734d42d217e426870eeb063e0a0f4e.js
streamlit_chat_animated/frontend/build/precache-manifest.7e3504a19fbc569e23c2a939fb946d5e.js
streamlit_chat_animated/frontend/build/precache-manifest.8824ed4ecf5825cb344cf9d35e20ccfa.js
streamlit_chat_animated/frontend/build/service-worker.js
streamlit_chat_animated/frontend/build/static/css/2.18bc7be3.chunk.css
streamlit_chat_animated/frontend/build/static/css/2.18bc7be3.chunk.css.map
streamlit_chat_animated/frontend/build/static/js/2.4143ccb6.chunk.js
streamlit_chat_animated/frontend/build/static/js/2.4143ccb6.chunk.js.LICENSE.txt
streamlit_chat_animated/frontend/build/static/js/2.4143ccb6.chunk.js.map
streamlit_chat_animated/frontend/build/static/js/2.9aa65565.chunk.js
streamlit_chat_animated/frontend/build/static/js/2.9aa65565.chunk.js.LICENSE.txt
streamlit_chat_animated/frontend/build/static/js/2.9aa65565.chunk.js.map
streamlit_chat_animated/frontend/build/static/js/2.c8026899.chunk.js
streamlit_chat_animated/frontend/build/static/js/2.c8026899.chunk.js.LICENSE.txt
streamlit_chat_animated/frontend/build/static/js/2.c8026899.chunk.js.map
streamlit_chat_animated/frontend/build/static/js/2.e5a6ec52.chunk.js
streamlit_chat_animated-0.0.3.2.dist-info/LICENSE
streamlit_chat_animated-0.0.3.2.dist-info/METADATA
streamlit_chat_animated-0.0.3.2.dist-info/WHEEL
streamlit_chat_animated-0.0.3.2.dist-info/top_level.txt
streamlit_chat_animated-0.0.3.2.dist-info/RECORD
