Metadata-Version: 2.1
Name: streamlit-chat-animated
Version: 0.0.3.2
Summary: A streamlit component, to make chatbots with text
Home-page: UNKNOWN
Author: Darin Manley
Author-email: darin.j.manley@gmail.com
License: UNKNOWN
Keywords: chat streamlit streamlit-component animated text
Platform: UNKNOWN
Classifier: Programming Language :: Python :: 3
Classifier: Operating System :: OS Independent
Requires-Python: >=3.8
License-File: LICENSE
Requires-Dist: streamlit (>=0.63)
